{
  "Темы": {
    "1": {
      "Название": "Огонь",
      "Иконка": "fire",
      "Основной цвет": "#ea5a4e",
      "Вторичный цвет": "#8B0000",
      "Группа": "Огонь"
    },
    "2": {
      "Название": "Вода",
      "Иконка": "water",
      "Основной цвет": "#54ade4",
      "Вторичный цвет": "#00008B",
      "Группа": "Вода"
    },
    "3": {
      "Название": "Пища",
      "Иконка": "food",
      "Основной цвет": "#54e380",
      "Вторичный цвет": "#006400",
      "Группа": "Пища"
    },
    "4": {
      "Название": "Жилье",
      "Иконка": "house",
      "Основной цвет": "#c2c1c1",
      "Вторичный цвет": "#505050",
      "Группа": "Жилье"
    },
    "5": {
      "Название": "Оружие",
      "Иконка": "weapon",
      "Основной цвет": "#f1ad47",
      "Вторичный цвет": "#654321",
      "Группа": "Оружие"
    },
    "6": {
      "Название": "Охота",
      "Иконка": "hunt",
      "Основной цвет": "#EE82EE",
      "Вторичный цвет": "#800080",
      "Группа": "Охота"
    }
  }
}